{
  "timestamp": "2025-09-19T16:11:34.211Z",
  "summary": {
    "totalPairs": 2,
    "strongInverse": 0,
    "moderateInverse": 0,
    "weakInverse": 1,
    "noCorrelation": 1
  },
  "results": [
    {
      "pair": "ARBUSDT/OPUSDT",
      "recommendation": "NO_CORRELATION",
      "confidence": 96,
      "stats": {
        "tokenA": "ARBUSDT",
        "tokenB": "OPUSDT",
        "totalDays": 200,
        "validDays": 200,
        "inverseCorrelationDays": 8,
        "inverseCorrelationPercentage": 4,
        "oppositeDirectionDays": 21,
        "oppositeDirectionPercentage": 10.5,
        "aOutperformsB": 108,
        "aOutperformsBPercentage": 54,
        "bOutperformsA": 92,
        "bOutperformsAPercentage": 46,
        "averageDifference": 0.227908117295298,
        "averageDifferenceWhenAUp": 1.8049291613360652,
        "averageDifferenceWhenBUp": -1.6233774561438634,
        "correlationCoefficient": 0.9139627070343778,
        "maxSingleDayDifference": 8.54335208443744,
        "minSingleDayDifference": -8.021515366572721,
        "consistencyScore": 76.54042734391251,
        "aVolatility": 5.774555796097786,
        "bVolatility": 5.389265746915068,
        "volatilityRatio": 1.0714921229117838,
        "maxConsecutiveInverseDays": 1,
        "currentConsecutiveInverseDays": 1
      },
      "strategyAdvice": "❌ SIN CORRELACIÓN INVERSA SIGNIFICATIVA: Solo 4.0% de días con correlación inversa.\n      Estrategia recomendada: Buscar otros pares de tokens o estrategias diferentes.\n\n📈 MÉTRICAS ADICIONALES:\n    • Días opuestos: 10.5%\n    • ARBUSDT supera a OPUSDT: 54.0%\n    • OPUSDT supera a ARBUSDT: 46.0%\n    • Volatilidad ARBUSDT: 5.77%\n    • Volatilidad OPUSDT: 5.39%\n    • Ratio volatilidad: 1.07\n    • Máximo consecutivo inverso: 1 días\n    • Consistencia: 76.5/100"
    },
    {
      "pair": "DOTUSDT/BTCUSDT",
      "recommendation": "WEAK_INVERSE",
      "confidence": 16.5,
      "stats": {
        "tokenA": "DOTUSDT",
        "tokenB": "BTCUSDT",
        "totalDays": 200,
        "validDays": 200,
        "inverseCorrelationDays": 33,
        "inverseCorrelationPercentage": 16.5,
        "oppositeDirectionDays": 48,
        "oppositeDirectionPercentage": 24,
        "aOutperformsB": 91,
        "aOutperformsBPercentage": 45.5,
        "bOutperformsA": 109,
        "bOutperformsAPercentage": 54.50000000000001,
        "averageDifference": -0.10745820032499591,
        "averageDifferenceWhenAUp": 2.1639856761715537,
        "averageDifferenceWhenBUp": -2.0038012531799136,
        "correlationCoefficient": 0.7259657066499452,
        "maxSingleDayDifference": 8.842709304115203,
        "minSingleDayDifference": -8.62517900434391,
        "consistencyScore": 73.6546666241804,
        "aVolatility": 3.7051735628202813,
        "bVolatility": 2.020773996066675,
        "volatilityRatio": 1.8335417864799315,
        "maxConsecutiveInverseDays": 3,
        "currentConsecutiveInverseDays": 1
      },
      "strategyAdvice": "📊 CORRELACIÓN INVERSA DÉBIL: 16.5% de días con correlación inversa.\n      Estrategia recomendada: Análisis adicional necesario antes de implementar estrategia contraria.\n\n📈 MÉTRICAS ADICIONALES:\n    • Días opuestos: 24.0%\n    • DOTUSDT supera a BTCUSDT: 45.5%\n    • BTCUSDT supera a DOTUSDT: 54.5%\n    • Volatilidad DOTUSDT: 3.71%\n    • Volatilidad BTCUSDT: 2.02%\n    • Ratio volatilidad: 1.83\n    • Máximo consecutivo inverso: 3 días\n    • Consistencia: 73.7/100"
    }
  ]
}